test/__init__.py
test/world.py
atestmodule-0.0.1.dist-info/METADATA
atestmodule-0.0.1.dist-info/WHEEL
atestmodule-0.0.1.dist-info/top_level.txt
atestmodule-0.0.1.dist-info/RECORD
